bibmania/__init__.py
bibtopia/__init__.py
cloudtopia/__init__.py
cloudwork/__init__.py
deeva/__init__.py
divinetouch/__init__.py
dtouch/__init__.py
evernaut/__init__.py
evernaut-0.0.0.dist-info/DESCRIPTION.rst
evernaut-0.0.0.dist-info/METADATA
evernaut-0.0.0.dist-info/RECORD
evernaut-0.0.0.dist-info/WHEEL
evernaut-0.0.0.dist-info/metadata.json
evernaut-0.0.0.dist-info/top_level.txt
evoila/__init__.py
nanolog/__init__.py
overture/__init__.py
