Metadata-Version: 2.0
Name: evernaut
Version: 0.0.0
Summary: evernaut library.
Home-page: UNKNOWN
Author: Dr. F
Author-email: UNKNOWN
License: GPLv3
Platform: UNKNOWN
Classifier: Development Status :: 3 - Alpha
Classifier: Programming Language :: Python :: 3
